
{
"BA_AppFramework" : "AppFramework ",
"RA_You_are_not_LoggedIn" : "Du er ikke logget på. Gå til Indstillinger, og log på",
"RA_OK" : "OK",
"RA_Cancel" : "Annuller",
"RA_Warning" : "ADVARSEL",
"RA_HomeScreen_Title" : "Startside for mobilapp",
"RA_SettingsScreen_Title" : "Kontoindstillinger",
"RA_SupportScreen_Title" : "Support",
"RA_DataServicesScreen_Title" : "Datatjenester",
"RA_DebugAndTestScreen_Title" : "Fejlfinding og test",
"RA_AboutScreen_Title" : "Om",
"RA_ConnectivityScreen_Title" : "Tilslutningsmuligheder",
"RA_SplashScreen_Title" : "Mobilapps",
"RA_PhilipsShopScreen_Title" : "Produkter",
"RA_HomeTab_Menu_Title" : "Forside",
"RA_Settings_Menu_Title" : "Indstillinger",
"RA_Support_Menu_Title" : "Support",
"RA_DataServices_Menu_Title" : "Datatjenester",
"RA_About_Menu_Title" : "Om",
"RA_Debug_and_Test_Menu_Title" : "Fejlfinding og test",
"RA_HomeScreen_Menu_Title" : "Startside for mobilapp",
"RA_ConnectivityScreen_Menu_Title" : "Tilslutningsmuligheder",
"RA_Philips_Shop_Menu_Title" : "Philips-butik",
"RA_Settings_Screen_Header_Title" : "Indstillinger",
"RA_Vertical_App_Setting_A" : "Lodret app-indstilling A",
"RA_Vertical_App_Setting_B" : "Lodret app-indstilling B",
"RA_Vertical_App_Setting_C" : "Lodret app-indstilling C",
"RA_Setting_Philips_Promo_Title" : "Modtag Philips' markedsføringsmateriale på baggrund af mine præferencer og min onlineadfærd",
"RA_Settings_Promo_Question_Text" : "Hvad betyder dette?",
"RA_Settings_Purchases" : "Køb",
"RA_Settings_OrderHistory" : "Ordrehistorik",
"RA_Settings_MyAccount" : "Min konto",
"RA_Settings_Logout" : "Log af",
"RA_Settings_Logout_Alert" : "Er du sikker på, at du vil logge af?",
"RA_Settings_Login" : "Log ind",
"RA_Skip_Button_Text" : "Skip",
"RA_Done_Button_Text" : "Udført",
"RA_HomeScreen_Header_Text" : "Tilbudsspecifik titel her ",
"RA_HomeScreen_Body_Text" : "Tilbudsspecifik stor tekst skal stå i brødteksten ",
"RA_WelcomeScreen_Title" : "Titel bundtilpasset",
"RA_WelcomeScreen_First_Text" : "Første fordelstekst er bundtilpasset",
"RA_WelcomeScreen_Second_Text" : "Anden fordelstekst er bundtilpasset",
"RA_WelcomeScreen_Third_Text" : "Tredje fordelstekst er bundtilpasset",
"BA_Add_Edit_Temp" : "Tilføj eller rediger temperatur ",
"BA_HSDP_login_not_available" : "HSDP-login ikke tilgængeligt",
"BA_Sync_Settings" : "Synkroniseringsindstillinger",
"RA_Connectivity_Measure_Value" : "Måleværdi",
"RA_Connectivity_Moment_Value" : "Øjebliksværdi",
"RA_Connectivity_Get_Measure_Value" : "Få måleværdien fra enheden",
"RA_Connectivity_Connection_Status_Connected" : "Tilsluttet",
"RA_Connectivity_Connection_Status_Disconnected" : "Afbrudt",
"RA_Connectivity_Get_Moment_Value" : "Få øjebliksværdi fra DataCore",
"RA_About_Description" : "Anmod Philips Design om at levere detaljer til beskrivelsesside",
"RA_Empty_Invalid_Data" : "Datafelt er tomt eller ugyldigt",
"RA_Invalid_Param_Msg" : "Du har indtastet eller valgt ugyldige parameterværdier. Vælg korrekte parameterværdier, og start igen",
"RA_NO_Order_History" : "Ordrehistorik ikke tilgængelig",
"RA_PR_Benefit_Text" : "Udvid din garanti med 24 måneder.\nFå 10 % rabat i Philips-butikken.\nFå gratis produkttilbehør",
"RA_PR_Extentende_Warranty" : "Din garantiperiode er blevet forlænget til næste år",
"RA_PR_Email_Text" : "Vi har sendt en e-mail til din e-mailadresse med kontrakten vedr. din forlængede garanti",
"RA_UR_Env_Alert" : "Skift konfiguration",
"RA_UR_Env_Alert_Msg" : "Konfigurationen kan kun ændres på opstartstidspunktet. Du skal genstarte appen for at ændre den",
"RA_Update_Userdata_Error" : "Der opstod en fejl under opdatering af brugerdata. Prøv igen senere",
"RA_Product_Registration_Text" : "Registrer dit produkt",
"RA_About_App_Version" : "Version",
"RA_DebugScreen_Title" : "Fejlfinding og test",
"RA_Setting_Philips_Promo_PartTwo" : "Markedsføringsmateriale baseret på mine præferencer og min onlineadfærd",
"RA_Settings_Update_Success" : "Opdatering udført",
"RA_Settings_Update_Fail" : "Opdatering mislykkedes",
"RA_Settings_Progress_Title" : "Vent venligst!!",
"RA_Settings_Progress_Message" : "Vent!!",
"RA_Logout_Failed" : "Log ud mislykkedes. Prøv igen",
"RA_CTN_Null" : "CTN er nul. Vælg eller indtast CTN-værdi",
"RA_Change_Configuration" : "Skift konfiguration",
"RA_Current_Configuration" : "Aktuel konfiguration",
"RA_Connectivity_DeviceID" : "Enhedsidentifikation",
"RA_Connectivity_ExampleID" : "Eksempel: 70:5A:0F:EC:CF:35",
"RA_Connectivity_DataCore_Not_Reachable" : "Der kan ikke oprettes forbindelse til Datacore-system",
"RA_Connectivity_Posting_Data" : "Datacore-systemet er ved at blive opdateret. Vent venligst",
"RA_Connectivity_Getting_Moment" : "Henter øjebliksværdier fra Datacore-systemet. Vent venligst",
"RA_Iap_Server_Error" : "Serverfejl",
"RA_Iap_No_Connection" : "Ingen forbindelse",
"RA_Iap_Connection_Time_Out" : "Forbindelsen fik timeout",
"RA_Iap_Authentication_Failure" : "Mislykket godkendelse",
"RA_Iap_Product_Out_Of_Stock" : "Produktet er ikke på lager",
"RA_reference_device_scan" : "Scanning af referenceenhed",
"RA_data_sync" : "Datasynkronisering",
"RA_add" : "Tilføj",
"RA_sync" : "Synkroniser",
"RA_update" : "Opdater",
"RA_delete" : "Slet",
"RA_registration" : "Registrering",
"RA_phase" : "Klokkeslæt",
"RA_temperature" : "Temperatur",
"RA_temparatute_hint" : "Babyens temperatur",
"RA_location" : "Noter",
"RA_location_hint" : "Stedets navn",
"RA_save" : "Gem",
"RA_synced" : "Ikke synkroniseret",
"RA_create_moment" : "Tilføj oplysninger",
"RA_invalid_temperature" : "Ugyldig temperaturangivelse",
"RA_consent" : "Brugerindhold",
"RA_set_characteristics" : "Brugeregenskaber",
"RA_view_characteristics" : "Vis egenskaber",
"RA_hide_characteristics" : "Skjul egenskaber",
"RA_edit" : "Redigér",
"RA_consents" : "Brugerindhold",
"RA_ble_ref_device" : "Bluetooth-ref.enhed",
"RA_unknown_device" : "Ukendt enhed",
"RA_no_device_found" : "Ingen enhed fundet",
"RA_something_wrong" : "Noget gik galt",
"RA_MYA_Consent_Moment_Text" : "da-I allow Philips to store my data in cloud",
"RA_MYA_Consent_Moment_Help" : "da-Giving this consent you are allowing Philips to store information related to you",
"RA_MYA_Consent_Coaching_Text" : "da-I allow Philips to use my data for Coaching purposes",
"RA_MYA_Consent_Coaching_Help" : "da-Giving this consent you are allowing Philips to process information related to you",
"RA_MYA_Consent_Binary_Text" : "da-I allow Philips to store binary data",
"RA_MYA_Consent_Binary_Help" : "da-Giving this consent you are allowing Philips to store information related to you",
"RA_MYA_Consent_Clickstream_Text" : "da-I allow Philips to use my mobile application usage statistics",
"RA_MYA_Consent_Clickstream_Help" : "da-Giving this consent you are allowing Philips to process mobile usage statistics related to you",
"RA_MYA_Consent_ResearchAnalytics_Text" : "da-I allow Philips to use my data for Research and Analytics purposes",
"RA_MYA_Consent_ResearchAnalytics_Help" : "da-Research and Analytics purpose explanation",
"RA_MYA_Marketing_Help_Text" : "da-As a result of your consent, Philips group companies may contact you with promotional communications via email, SMS and other digital channels, such as mobile apps and social media. To be able to tailor the communications to your preferences and behavior and provide you with the best, personalized experience, we may analyze and combine your personal data. This data may include: \n\nData you give us\nData that you want to actively share with us such as: your name, date of birth or age, email address, physical address, country, gender, phone number, social media profile.\n\nData we get from your interactions with Philips\nData about your interactions and usage of the Philips digital channels, such as social media, websites, emails, apps and connected products. This data may include: IP address, cookies, device information, communications you click on, location details, and websites you visit\n\nPhilips will give you the opportunity to withdraw your consent at any time.\nFor more information, please read the Philips Privacy notice and the Philips Cookie notice.",
