
{
"BA_AppFramework" : "FrameworkApp ",
"RA_You_are_not_LoggedIn" : "Accesso non eseguito. Andare a Impostazioni e selezionare Accedi",
"RA_OK" : "OK",
"RA_Cancel" : "Annulla",
"RA_Warning" : "AVVISO",
"RA_HomeScreen_Title" : "Home app mobile",
"RA_SettingsScreen_Title" : "Impostazioni account",
"RA_SupportScreen_Title" : "Assistenza",
"RA_DataServicesScreen_Title" : "Servizi di dati",
"RA_DebugAndTestScreen_Title" : "Debug e test",
"RA_AboutScreen_Title" : "Informazioni su",
"RA_ConnectivityScreen_Title" : "Connettività",
"RA_SplashScreen_Title" : "App mobili",
"RA_PhilipsShopScreen_Title" : "Prodotti",
"RA_HomeTab_Menu_Title" : "Home",
"RA_Settings_Menu_Title" : "Impostazioni",
"RA_Support_Menu_Title" : "Assistenza",
"RA_DataServices_Menu_Title" : "Servizi di dati",
"RA_About_Menu_Title" : "Informazioni su",
"RA_Debug_and_Test_Menu_Title" : "Debug e test",
"RA_HomeScreen_Menu_Title" : "Home app mobile",
"RA_ConnectivityScreen_Menu_Title" : "Connettività",
"RA_Philips_Shop_Menu_Title" : "Negozio Philips",
"RA_Settings_Screen_Header_Title" : "Impostazioni",
"RA_Vertical_App_Setting_A" : "Impostazione app verticale A",
"RA_Vertical_App_Setting_B" : "Impostazione app verticale B",
"RA_Vertical_App_Setting_C" : "Impostazione app verticale C",
"RA_Setting_Philips_Promo_Title" : "Ricevi comunicazioni promozionali Philips in base alle tue preferenze e al tuo comportamento di acquisto online",
"RA_Settings_Promo_Question_Text" : "Che cosa significa?",
"RA_Settings_Purchases" : "Acquisti",
"RA_Settings_OrderHistory" : "Cronologia degli ordini",
"RA_Settings_MyAccount" : "Account personale",
"RA_Settings_Logout" : "Esci",
"RA_Settings_Logout_Alert" : "Uscire?",
"RA_Settings_Login" : "Accedi",
"RA_Skip_Button_Text" : "Ignora",
"RA_Done_Button_Text" : "Fatto",
"RA_HomeScreen_Header_Text" : "Inserire qui il titolo specifico della proposta ",
"RA_HomeScreen_Body_Text" : "Inserire nel corpo il testo di grandi dimensioni specifico della proposta ",
"RA_WelcomeScreen_Title" : "Titolo allineato in basso",
"RA_WelcomeScreen_First_Text" : "Testo primo vantaggio allineato in basso",
"RA_WelcomeScreen_Second_Text" : "Testo secondo vantaggio allineato in basso",
"RA_WelcomeScreen_Third_Text" : "Testo terzo vantaggio allineato in basso",
"BA_Add_Edit_Temp" : "Aggiungi o modifica temperatura ",
"BA_HSDP_login_not_available" : "Accesso HSDP non disponibile",
"BA_Sync_Settings" : "Impostazioni di sincronizzazione",
"RA_Connectivity_Measure_Value" : "Valore misura",
"RA_Connectivity_Moment_Value" : "Valore momento",
"RA_Connectivity_Get_Measure_Value" : "Ottieni valore misura dal dispositivo",
"RA_Connectivity_Connection_Status_Connected" : "Collegato",
"RA_Connectivity_Connection_Status_Disconnected" : "Scollegato",
"RA_Connectivity_Get_Moment_Value" : "Ottieni valore momento da DataCore",
"RA_About_Description" : "Richiedi Philips Design per inserire dettagli nella pagina di descrizione",
"RA_Empty_Invalid_Data" : "Campo Dati vuoto o non valido",
"RA_Invalid_Param_Msg" : "I valori dei parametri inseriti o selezionati non sono validi. Selezionare valori dei parametri corretti e riavviare",
"RA_NO_Order_History" : "Cronologia degli ordini non disponibile",
"RA_PR_Benefit_Text" : "Estendi la garanzia per altri 24 mesi.\nRicevi uno sconto del 10% sui prodotti acquistati nel negozio Philips.\nRicevi gratis accessori per il prodotto",
"RA_PR_Extentende_Warranty" : "Il tuo periodo di garanzia è stato esteso fino al prossimo anno",
"RA_PR_Email_Text" : "Abbiamo inviato un'e-mail con il contratto di estensione della garanzia al tuo indirizzo e-mail",
"RA_UR_Env_Alert" : "Modifica configurazione",
"RA_UR_Env_Alert_Msg" : "La configurazione è modificabile solo all'avvio. Riavvia l'applicazione per effettuare modifiche",
"RA_Update_Userdata_Error" : "Si è verificato un errore durante l'aggiornamento delle informazioni in Dati utente. Riprovare più tardi",
"RA_Product_Registration_Text" : "Registra il prodotto",
"RA_About_App_Version" : "Versione",
"RA_DebugScreen_Title" : "Debug e test",
"RA_Setting_Philips_Promo_PartTwo" : "Comunicazioni promozionali in base alle tue preferenze personali e al tuo comportamento di acquisto online",
"RA_Settings_Update_Success" : "Aggiornamento eseguito",
"RA_Settings_Update_Fail" : "Aggiornamento non riuscito",
"RA_Settings_Progress_Title" : "Attendere.",
"RA_Settings_Progress_Message" : "Attendi.",
"RA_Logout_Failed" : "Disconnessione non riuscita. Riprovare.",
"RA_CTN_Null" : "CTN con parametro nullo. Selezionare o inserire un valore CTN",
"RA_Change_Configuration" : "Modifica configurazione",
"RA_Current_Configuration" : "Configurazione corrente",
"RA_Connectivity_DeviceID" : "ID dispositivo",
"RA_Connectivity_ExampleID" : "Esempio: 70:5A:0F:EC:CF:35",
"RA_Connectivity_DataCore_Not_Reachable" : "Impossibile stabilire la connessione con il sistema Datacore",
"RA_Connectivity_Posting_Data" : "Aggiornamento in corso del sistema DataCore. Attendere.",
"RA_Connectivity_Getting_Moment" : "Recupero valori momento in corso dal sistema Datacore. Attendere.",
"RA_Iap_Server_Error" : "Errore del server",
"RA_Iap_No_Connection" : "Nessuna connessione",
"RA_Iap_Connection_Time_Out" : "Timeout della connessione",
"RA_Iap_Authentication_Failure" : "Autenticazione non riuscita",
"RA_Iap_Product_Out_Of_Stock" : "Prodotto esaurito",
"RA_reference_device_scan" : "Scansione dispositivo di riferimento",
"RA_data_sync" : "Sincronizzazione dati",
"RA_add" : "Aggiungi",
"RA_sync" : "Sincronizza",
"RA_update" : "Aggiorna",
"RA_delete" : "Elimina",
"RA_registration" : "Registrazione",
"RA_phase" : "Ora del giorno",
"RA_temperature" : "Temperatura",
"RA_temparatute_hint" : "Temperatura del bambino",
"RA_location" : "Note",
"RA_location_hint" : "Nome del luogo",
"RA_save" : "Salva",
"RA_synced" : "Non sincronizzato",
"RA_create_moment" : "Crea momento",
"RA_invalid_temperature" : "Dato temperatura non valido",
"RA_consent" : "Consensi utente",
"RA_set_characteristics" : "Caratteristiche utente",
"RA_view_characteristics" : "Vedi caratteristiche",
"RA_hide_characteristics" : "Nascondi caratteristiche",
"RA_edit" : "Modifica",
"RA_consents" : "Consensi utente",
"RA_ble_ref_device" : "dispositivo di riferimento Bluetooth",
"RA_unknown_device" : "Dispositivo sconosciuto",
"RA_no_device_found" : "Nessun dispositivo trovato",
"RA_something_wrong" : "Si è verificato un problema",
"":"" }
