{
  "project_info": {
    "project_number": "982961796297",
    "firebase_url": "https://com-philips-appinfra-demo.firebaseio.com",
    "project_id": "com-philips-appinfra-demo",
    "storage_bucket": "com-philips-appinfra-demo.appspot.com"
  },
  "client": [
    {
      "client_info": {
        "mobilesdk_app_id": "1:982961796297:android:ab885084a2988c88",
        "android_client_info": {
          "package_name": "com.philips.platform.appinfra.demoapp"
        }
      },
      "oauth_client": [
        {
          "client_id": "982961796297-4benp873ps48apqq3jejifho2a0gnglj.apps.googleusercontent.com",
          "client_type": 3
        }
      ],
      "api_key": [
        {
          "current_key": "AIzaSyAQc4wBTgUmTreMyRChB0fTHkq4cvrbvns"
        }
      ],
      "services": {
        "analytics_service": {
          "status": 1
        },
        "appinvite_service": {
          "status": 1,
          "other_platform_oauth_client": []
        },
        "ads_service": {
          "status": 2
        }
      }
    }
  ],
  "configuration_version": "1"
}